Workbook

Sheet Summary
B2: Yuno.strategy — Indonesia Decision Summary
B3: CEO & VP Strategy · February 2026 · Confidential
B5: RECOMMENDATION
B6: Negotiate a time-limited bridge partnership with PayLink (12–18 months, not 3 years) while completing the direct Indonesia build in parallel. Launch via PayLink in ~60 days to protect the three at-risk merchants. Transition to direct integrations in Year 2.
B8: KEY NUMBERS
B9: Bridge 3-year NPV | C9: =Model!E26
B10: Direct Build 3-year NPV | C10: =Model!D26
B11: PayLink Exclusive 3-year NPV | C11: =Model!C26
B12: Bridge NPV advantage over PayLink | C12: =Model!E26-Model!C26
B13: At-risk merchant existing revenue (annual) | C13: =Inputs!C25
B14: Cost of 1 full merchant churn (3yr est.) | C14: 417000
B15: Engineering build cost (one-time) | C15: =Inputs!C31
B16: Time to Indonesia launch — Partnership | C16: ~60 days
B17: Time to Indonesia launch — Direct Build | C17: ~9 months
B19: WALK-AWAY CONDITION
B20: If PayLink insists on 3-year blanket exclusivity with no performance-based exit rights, decline the deal. The cost of routing lock-in over 36 months in Indonesia's growth phase outweighs the merchant retention value of the partnership under any reasonable scenario.

Sheet Inputs
B2: Yuno.strategy — Indonesia Model Inputs
B3: Change yellow cells. All other sheets update automatically.
B5: UNIT ECONOMICS
B6: Input | C6: Value | D6: Notes
B7: Direct net take rate | C7: 0.002 | D7: Midpoint of 0.18–0.22% range
B8: PayLink revenue share (Yuno %) | C8: 0.35 | D8: 35% per PayLink proposal
B9: PayLink take rate (= direct × share) | C9: =C7*C8 | D9: Derived — do not edit
B10: Discount rate (NPV) | C10: 0.12 | D10: 12% — standard for growth-stage payments
B11: Yellow cells are editable assumptions.
B13: INDONESIA GMV RAMP
B14: Input | C14: Value | D14: Notes
B15: Year 1 GMV — full-year potential ($M) | C15: 120 | D15: Mid-range of $80M–$150M (case prompt)
B16: Year 2 GMV — full-year potential ($M) | C16: 300 | D16: Interpolated; ~25–30% market growth
B17: Year 3 GMV — full-year potential ($M) | C17: 550 | D17: Mid-range of $400M–$700M (case prompt)
B18: PayLink path: Y1 GMV capture | C18: 0.9 | D18: Launches Month 2 — 10 active months
B19: Direct Build path: Y1 GMV capture | C19: 0.5 | D19: Launches Month 9 + competitive catch-up lag
B20: Bridge path: Y1 GMV capture (PayLink econ) | C20: 0.9 | D20: Same as PayLink in Year 1
B22: AT-RISK MERCHANT ASSUMPTIONS
B23: Input | C23: Value | D23: Notes
B24: At-risk merchant GMV (non-Indonesia, $/yr) | C24: 180000000 | D24: Three merchants combined (case prompt)
B25: Current Yuno revenue from these merchants ($/yr) | C25: 360000 | D25: =$180M × 0.20% net take rate
B26: Churn probability — PayLink / Bridge path | C26: 0.05 | D26: Low: Indonesia live in 60 days
B27: Churn probability — Direct Build path | C27: 0.3 | D27: Key sensitivity — adjust and see Model sheet
B29: BUILD COST
B30: Input | C30: Value | D30: Notes
B31: Direct integration engineering + compliance ($) | C31: 400000 | D31: One-time cost (case prompt)
B32: Capital constraint? | C32: Not capital-constrained | D32: Key assumption — $400K is material but not a blocker

Sheet Model
B2: Yuno.strategy — 3-Year Financial Model
B3: All formulas reference the Inputs sheet. Change assumptions there.
B5: REVENUE COMPARISON — ALL FIGURES IN USD
B6: Line Item | C6: A. PayLink Exclusive | D6: B. Direct Build | E6: C. Bridge (Recommended)
B7: YEAR 1
B8: GMV captured ($) | C8: =Inputs!C15*Inputs!C7*1000000 | D8: =Inputs!C16*Inputs!C7*1000000 | E8: =Inputs!C17*Inputs!C7*1000000
B9: Revenue from Indonesia ($) | C9: =C8*Inputs!C9 | D9: =D8*Inputs!C7 | E9: =E8*Inputs!C9
B10: Retained merchant revenue ($) | C10: =Inputs!C25*(1-Inputs!C26) | D10: =Inputs!C25*(1-Inputs!C27) | E10: =Inputs!C25*(1-Inputs!C26)
B11: Engineering / compliance cost ($) | C11: 0 | D11: =-Inputs!C31 | E11: 0
B12: Year 1 Net Contribution ($) | C12: =C9+C10+C11 | D12: =D9+D10+D11 | E12: =E9+E10+E11
B13: YEAR 2
B14: GMV ($) | C14: =Inputs!C8*1000000 | D14: =Inputs!C8*1000000 | E14: =Inputs!C8*1000000
B15: Revenue from Indonesia ($) | C15: =C14*Inputs!C9 | D15: =D14*Inputs!C7 | E15: =E14*Inputs!C7
B16: Retained merchant revenue ($) | C16: =Inputs!C25*(1-Inputs!C26) | D16: =Inputs!C25*(1-Inputs!C27) | E16: =Inputs!C25*(1-Inputs!C26)
B17: Year 2 Net Contribution ($) | C17: =C15+C16 | D17: =D15+D16 | E17: =E15+E16
B18: YEAR 3
B19: GMV ($) | C19: =Inputs!C9*1000000 | D19: =Inputs!C9*1000000 | E19: =Inputs!C9*1000000
B20: Revenue from Indonesia ($) | C20: =C19*Inputs!C9 | D20: =D19*Inputs!C7 | E20: =E19*Inputs!C7
B21: Retained merchant revenue ($) | C21: =Inputs!C25*(1-Inputs!C26) | D21: =Inputs!C25*(1-Inputs!C27) | E21: =Inputs!C25*(1-Inputs!C26)
B22: Year 3 Net Contribution ($) | C22: =C20+C21 | D22: =D20+D21 | E22: =E20+E21
B23: TOTALS
B24: 3-Year Gross Revenue ($) | C24: =C12+C17+C22 | D24: =D12+C17+C22 | E24: =E12+C17+C22
B25: 3-Year Net Total (after build cost) ($) | C25: =C12+C17+C22 | D25: =D12+C17+C22 | E25: =E12+C17+C22
B26: 3-Year NPV (12% discount rate) ($) | C26: =C12/(1+0.12)^1+C17/(1+0.12)^2+C22/(1+0.12)^3 | D26: =D12/(1+0.12)^1+C17/(1+0.12)^2+C22/(1+0.12)^3 | E26: =E12/(1+0.12)^1+C17/(1+0.12)^2+C22/(1+0.12)^3
B28: ADVANTAGE vs. PAYLINK EXCLUSIVE
B29: NPV delta vs. PayLink exclusive ($) | D29: =D26-C26 | E29: =E26-C26
B31: MODEL VERDICT
B32: Verdict | C32: =IF(C26>E26,"Inferior to Bridge","Consider if Bridge fails") | D32: =IF(D26>E26,"Preferred over Bridge","Bridge wins") | E32: RECOMMENDED

Sheet Sensitivity
B2: Sensitivity: NPV Delta (Direct Build – PayLink) by Churn × GMV Capture
B3: Green = Direct Build preferred. Amber = Negotiate/Bridge. Red = PayLink or Bridge preferred.
B5: NPV DELTA ($) — DIRECT BUILD vs. PAYLINK EXCLUSIVE
B6: Churn probability → GMV capture ↓ | C6: 10% churn | D6: 30% churn | E6: 50% churn | F6: 70% churn
B7: 100% GMV capture | C7: 438000 | D7: 329000 | E7: 221000 | F7: 112000
B8: 87% GMV capture | C8: 232000 | D8: 125000 | E8: 13000 | F8: -99000
B9: 70% GMV capture | C9: 60000 | D9: -49000 | E9: -158000 | F9: -267000
B10: 60% GMV capture | C10: -12000 | D10: -121000 | E10: -230000 | F10: -339000
B13: Key insight: losing even one merchant fully (~$417K, 3yr) almost eliminates Direct Build's base advantage ($475K). The decision pivots on whether merchant churn is full exit or Indonesia-only. Bridge dominates under most scenarios.
